sigutils/__init__.py
sigutils/_util.py
sigutils/_version.py
sigutils/fdls.py
sigutils/plot.py
sigutils/tests/__init__.py
sigutils/tests/test__init__.py
sigutils/tests/test_fdls.py
sigutils/tests/test_plot.py
sigutils/tests/test_sigutils.py
sigutils/tests/test_util.py
sigutils-0.2.5.dist-info/DESCRIPTION.rst
sigutils-0.2.5.dist-info/METADATA
sigutils-0.2.5.dist-info/RECORD
sigutils-0.2.5.dist-info/WHEEL
sigutils-0.2.5.dist-info/metadata.json
sigutils-0.2.5.dist-info/top_level.txt
